CHANGELOG.rst
LICENSE.txt
MANIFEST.in
README.rst
TODO.rst
VERSION.txt
setup.cfg
setup.py
test-requirements.txt
ejabberd_htpasswd/__init__.py
ejabberd_htpasswd/cli.py
ejabberd_htpasswd/engine.py
ejabberd_htpasswd/htpasswd.py
ejabberd_htpasswd/i18n.py
ejabberd_htpasswd.egg-info/PKG-INFO
ejabberd_htpasswd.egg-info/SOURCES.txt
ejabberd_htpasswd.egg-info/dependency_links.txt
ejabberd_htpasswd.egg-info/entry_points.txt
ejabberd_htpasswd.egg-info/requires.txt
ejabberd_htpasswd.egg-info/top_level.txt
ejabberd_htpasswd.egg-info/zip-safe