Metadata-Version: 1.1
Name: ejabberd-htpasswd
Version: 0.1.3
Summary: Yet another ejabberd authentication bridge that uses apache-style htpasswd files
Home-page: http://github.com/metagriffin/ejabberd-htpasswd
Author: metagriffin
Author-email: mg.pypi@metagriffin.net
License: GPLv3+
Keywords: ejabberd external authentication apache htpasswd
Platform: any
Classifier: Development Status :: 4 - Beta
Classifier: Environment :: Console
Classifier: Intended Audience :: Developers
Classifier: Intended Audience :: System Administrators
Classifier: Natural Language :: English
Classifier: Operating System :: OS Independent
Classifier: Programming Language :: Python
Classifier: Topic :: Software Development
Classifier: Topic :: Software Development :: Libraries :: Python Modules
Classifier: Topic :: Utilities
Classifier: License :: OSI Approved :: GNU General Public License v3 or later (GPLv3+)
